{
    "AdiaosNN": [
        41656,
        "Neo: Shaman",
        "e59bb6dca998da63697717cbad5221b1"
    ],
    "AliNivalis": [
        44235,
        "Neo: Shaman",
        "571e7378016f7bf11b8e006aabc1b3ec"
    ],
    "AlphaD": [
        44102,
        "Neo: Shaman",
        "a21704ca80e02424ecb90d19d9debe6b"
    ],
    "Amane": [
        41392,
        "Neo: Shaman",
        "62fbe2f57c2a75183a2b2957409537c9"
    ],
    "AmberLynx": [
        43332,
        "Neo: Shaman",
        "973c4d78c7461e6fa5fd8a22e00946c8"
    ],
    "AzureParagon": [
        43449,
        "Neo: Shaman",
        "dbcccea3207c244abff0d30d2270180d"
    ],
    "BeadMistress": [
        46446,
        "Neo: Shaman",
        "1ade3da7f0106bf6339ccaf7429fe5f9"
    ],
    "BidenBlaster": [
        41117,
        "Neo: Shaman",
        "5d25da90ad731e8976116a1fc0329701"
    ],
    "Ccuteskittie": [
        44243,
        "Neo: Shaman",
        "01d487ef1d210fed8df8cbfffb59c86d"
    ],
    "Celestifur": [
        46755,
        "Neo: Shaman",
        "d0e326e314f3b4a765087036051d8ac1"
    ],
    "ChicKenHat": [
        42069,
        "Neo: Shaman",
        "454c37975f15ad939ef189835a7e15fa"
    ],
    "ClaireAkeno": [
        40264,
        "Neo: Shaman",
        "dbc366274d159768decc50ca76045994"
    ],
    "CoffeeLily": [
        44149,
        "Neo: Shaman",
        "061f4af81f4f656b0ec0af0b8d534fa9"
    ],
    "DiceShrine": [
        46478,
        "Neo: Shaman",
        "174c869dd6e4aee06da1c8c7f1ec9859"
    ],
    "DimSorcery": [
        42446,
        "Neo: Shaman",
        "9b821714d58c48cb8a5076bf90f4316c"
    ],
    "DirtyGirlX": [
        47981,
        "Neo: Shaman",
        "6030441051dbea33dbe1c28907e5933f"
    ],
    "Domanis": [
        43345,
        "Neo: Shaman",
        "8a5af7bce63292f3c4f00d8bbb472df0"
    ],
    "Ekdud": [
        47732,
        "Neo: Shaman",
        "3a83e8a2584dbbddf94fb87d9774c605"
    ],
    "ElderTiamat": [
        41555,
        "Neo: Shaman",
        "814da6c95348afef828849b11ebadfbb"
    ],
    "Elezabeth": [
        43392,
        "Neo: Shaman",
        "f9f61b1099e7a72809c5b985586cbf46"
    ],
    "Evandel": [
        42283,
        "Neo: Shaman",
        "f3ff423c32dd274127eaaf3179d1b97a"
    ],
    "FaintDream": [
        43020,
        "Neo: Shaman",
        "23be61d089a9f9b9d960d982c4cbde14"
    ],
    "FanLaNorne": [
        41476,
        "Neo: Shaman",
        "69f9b9a90e4767c69a37cddc1c58b2f4"
    ],
    "FeelsTakaMan": [
        42433,
        "Neo: Shaman",
        "20eb4950b4d651d697e5dab7a901e6c7"
    ],
    "FrankyZN": [
        40752,
        "Neo: Shaman",
        "f63e965aff009a5d1f849d2b442c2722"
    ],
    "GenoSyde": [
        43783,
        "Neo: Shaman",
        "0fda83c31f7d60f8c6c8edaf3ed222ea"
    ],
    "HDshaman": [
        47172,
        "Neo: Shaman",
        "507f84f1afeb050c8ff1bce818f46dfe"
    ],
    "Hakure1Reimu": [
        41697,
        "Neo: Shaman",
        "0bdf9347d3733f665626a59a559720cb"
    ],
    "HeavenPigger": [
        43022,
        "Neo: Shaman",
        "f491ed49659356ccd8081c628b600653"
    ],
    "IWantDI": [
        45041,
        "Neo: Shaman",
        "afef1eafb5ed0c72a1f46cd0293e219f"
    ],
    "Iamtoolazy": [
        41222,
        "Neo: Shaman",
        "21f270e6fdfd54f1ecaadeaebd958ccd"
    ],
    "InDivWeTrust": [
        43644,
        "Neo: Shaman",
        "f398c5f7f9f2d0b1a5b348f387b79396"
    ],
    "JadeQuandary": [
        44119,
        "Neo: Shaman",
        "89a4503d4f66d8065309aee2fbd6d04c"
    ],
    "Jallehbeens": [
        44648,
        "Neo: Shaman",
        "04770fcbf6393bb8ebf4a97e9c5f5e61"
    ],
    "JellyBead": [
        48375,
        "Neo: Shaman",
        "57fddfde89c1a3de4f78b3622b7d66a4"
    ],
    "Jigglypuff27": [
        44292,
        "Neo: Shaman",
        "0aaf9a4115fecc2536e4fb68024bd0db"
    ],
    "JomsLL": [
        41127,
        "Neo: Shaman",
        "9c22111c7086ef591a229ab11e201736"
    ],
    "Kagome": [
        43903,
        "Neo: Shaman",
        "3b289da5e277b7f6ba9aea2a2976d5eb"
    ],
    "Karisan": [
        41352,
        "Neo: Shaman",
        "3be89a23dfadd9a06ace3dc67d5d3b91"
    ],
    "Kizali": [
        41682,
        "Neo: Shaman",
        "c6cbb1fd37a25422e89e0fed4f82a7de"
    ],
    "Kousha": [
        42775,
        "Neo: Shaman",
        "8b25409816d95e4f775d622c09943692"
    ],
    "Lessons": [
        40652,
        "Neo: Shaman",
        "4e92f9fc63534342b9275248f45b0307"
    ],
    "Lmagician7": [
        43992,
        "Neo: Shaman",
        "58eb95bfcb6de87312c4ea3216d7dfc3"
    ],
    "Luminousa": [
        45927,
        "Neo: Shaman",
        "9da411d393340534390f9f637a5f1778"
    ],
    "Lusamie": [
        42308,
        "Neo: Shaman",
        "3684679908455952be4cd0f399526ed5"
    ],
    "MikoForbae": [
        40637,
        "Neo: Shaman",
        "33a75690696111272fdb00ee84360710"
    ],
    "MikoSaki": [
        44890,
        "Neo: Shaman",
        "3bf02cbfdb33cb778cf995bbfbff8928"
    ],
    "MikoSlime": [
        44898,
        "Neo: Shaman",
        "4d689eeb8491d2797f1933e25fce13bc"
    ],
    "Mingtum": [
        44608,
        "Neo: Shaman",
        "1682bdd82ed37144c4e3c5bab99d37ac"
    ],
    "MintRosary": [
        44520,
        "Neo: Shaman",
        "e8c7c482cb104b39eb36d8dc82275ab6"
    ],
    "Miokono": [
        42495,
        "Neo: Shaman",
        "bd74ec055b0f53b093f83e4dc54170d1"
    ],
    "Mooko": [
        41401,
        "Neo: Shaman",
        "8096dbbf759480f0d1dbfb2e2c9562df"
    ],
    "Nayutah": [
        44415,
        "Neo: Shaman",
        "3abe17e0104dec1365164d8ec1449417"
    ],
    "NomadUS": [
        43975,
        "Neo: Shaman",
        "9f9afced793d796b4c98ede0b2164ff3"
    ],
    "Pettanko": [
        44160,
        "Neo: Shaman",
        "fffa93d4f063ee84ed4a9a1bbe4377fe"
    ],
    "Precede": [
        45644,
        "Neo: Shaman",
        "3384f7545a9d6e67be95d8ea1f960ce0"
    ],
    "Priestnnynn": [
        44391,
        "Neo: Shaman",
        "3a43d6543005657a1da49de4965eae56"
    ],
    "PuppyRose": [
        41168,
        "Neo: Shaman",
        "e7817472d2980dc9d333b4aa9f52a1c1"
    ],
    "RainyLY": [
        44021,
        "Neo: Shaman",
        "7c95b877a14f4721f0664f61d96f4f4a"
    ],
    "Renabi": [
        41256,
        "Neo: Shaman",
        "c22eaa44d0175c4f4cf1af1af208b5c8"
    ],
    "RicottaBar": [
        45494,
        "Neo: Shaman",
        "7a81c0927963b20277a3dc602f9257b8"
    ],
    "RisekoLong": [
        41382,
        "Neo: Shaman",
        "28b6ab7a2788749279c1dd29012c2141"
    ],
    "Riwie": [
        44414,
        "Neo: Shaman",
        "9d5706bdb913edfa64135a4fb9a1669a"
    ],
    "Ryuika": [
        44855,
        "Neo: Shaman",
        "a986aab6bd88ee728e4d4d6628a0ce62"
    ],
    "Sagume": [
        44035,
        "Neo: Shaman",
        "8ab6a2d2839147c46558b0ba1b842504"
    ],
    "SaintTaill": [
        46436,
        "Neo: Shaman",
        "2a7626b87e7c806ab1106658b7a94635"
    ],
    "SeiryuNoHana": [
        42287,
        "Neo: Shaman",
        "d1f1d11bd71bddd4b675bfb3d478e8a7"
    ],
    "ShamanDar": [
        41596,
        "Neo: Shaman",
        "8d7ac19fb9519cc7492f3d6e3a1c921c"
    ],
    "Shibiku": [
        43818,
        "Neo: Shaman",
        "f9d8bacf73f5d8413ce2f8ce7632dea9"
    ],
    "SoyJuanPa": [
        43411,
        "Neo: Shaman",
        "a5bb46bf82a2f3a529641b4fef64be48"
    ],
    "Spherulitic": [
        43136,
        "Neo: Shaman",
        "e26f4be5821e07fb230ebc16918db406"
    ],
    "TWmagic": [
        40720,
        "Neo: Shaman",
        "63fadf569490bac2950dbff1fd1896f5"
    ],
    "Tamagushi": [
        46303,
        "Neo: Shaman",
        "d4167fef69afd780ee58858f9a5090cf"
    ],
    "Tasilius": [
        44082,
        "Neo: Shaman",
        "4eaa968cb43859c84ae8e012576d5d81"
    ],
    "Tuctu": [
        45138,
        "Neo: Shaman",
        "3205d1f3a38cd9f933cc2e0d8df640b5"
    ],
    "VyVily": [
        45603,
        "Neo: Shaman",
        "09c63f1ecc8bcd8c83f5ef5fec59300f"
    ],
    "Xinwhaleeee": [
        43550,
        "Neo: Shaman",
        "94470ca0e335b2a70b8b82f1083a7b37"
    ],
    "abing6666666": [
        43090,
        "Neo: Shaman",
        "7bb5554ca03e8fbea02f5526ab6a275b"
    ],
    "babydong20": [
        41330,
        "Neo: Shaman",
        "fdc0521dae648b3c316c495ac77f90fb"
    ],
    "dragondau": [
        44152,
        "Neo: Shaman",
        "05f2e4664af8f0a4ee22e412c8769817"
    ],
    "jlee15": [
        46966,
        "Neo: Shaman",
        "57de534b613af09da7d07bb1b6de8d06"
    ],
    "lLightMahonl": [
        46277,
        "Neo: Shaman",
        "f284bb6e023aaa8ea2e11def160941af"
    ],
    "lkdasa": [
        40698,
        "Neo: Shaman",
        "66f44841b9a6110be6dfc3e1f3bb6892"
    ],
    "soysfox": [
        44431,
        "Neo: Shaman",
        "0ceaf7c143270aca0ae032808ae986f4"
    ],
    "xRaymoox": [
        45017,
        "Neo: Shaman",
        "5f5999434bb9caa8bb6d4276c59135e8"
    ],
    "xSailor-Sunx": [
        40547,
        "Neo: Shaman",
        "54ff64a05434b5bfec11c6de669243d2"
    ],
    "xSangatsu": [
        44645,
        "Neo: Shaman",
        "1a1a6c10f775443abe8e75a054402a8d"
    ],
    "yoyBB": [
        46708,
        "Neo: Shaman",
        "e9c64dca817a2dfaf6041ce4453d7632"
    ]
}