{
    "Akumapon": [
        41507,
        "Neo: Dimension Walker",
        "2b08a680f5fa830346c9397ddbea2c09"
    ],
    "Ascende": [
        40286,
        "Neo: Dimension Walker",
        "8aabee22b1ba283d3e28e08b3ebbbfa7"
    ],
    "Astergem": [
        44368,
        "Neo: Dimension Walker",
        "009318796451c9f2c40a585cac1d04e8"
    ],
    "Azathothq": [
        45875,
        "Neo: Dimension Walker",
        "4670ecbc876679e1c1348c749d0d276e"
    ],
    "BaChe2": [
        47174,
        "Neo: Dimension Walker",
        "b732b517f5a7c8b257cfb48922433ced"
    ],
    "Basdon": [
        44238,
        "Neo: Dimension Walker",
        "1ed71424acc6c9fbb9128d327a0a95e2"
    ],
    "Blinkish": [
        47075,
        "Neo: Dimension Walker",
        "5095eac141046ef1f63704711893f477"
    ],
    "BlooSpace": [
        40015,
        "Neo: Dimension Walker",
        "ff7ef959f678dc2011837741e921547b"
    ],
    "Chardo": [
        46488,
        "Neo: Dimension Walker",
        "7b18b17beaf792304257c898752009c8"
    ],
    "DRDiWa1ker": [
        42444,
        "Neo: Dimension Walker",
        "22acd2b86362483f4c1a0fdb1e91ce30"
    ],
    "DimensionMos": [
        43958,
        "Neo: Dimension Walker",
        "fe82cf07f99f0888e619aba0d05263da"
    ],
    "DreadLighttt": [
        43198,
        "Neo: Dimension Walker",
        "1885c1361becca3be42ca4ff7f57624e"
    ],
    "EdgyEmo": [
        40267,
        "Neo: Dimension Walker",
        "de838a7c28d40216751fc292c44cffad"
    ],
    "EternalEmo": [
        43479,
        "Neo: Dimension Walker",
        "27c17b2a16881f810063bf3dd25a87d1"
    ],
    "FateAverrun": [
        41274,
        "Neo: Dimension Walker",
        "48efaafac89ae1151a8eec7aa8a256e7"
    ],
    "Felspar": [
        40437,
        "Neo: Dimension Walker",
        "500f9badd86e61b4a3536b789dc263c9"
    ],
    "GothBF": [
        45917,
        "Neo: Dimension Walker",
        "b429e5a36d6d6ffd6360575cf418aeba"
    ],
    "HentaiFab": [
        42254,
        "Neo: Dimension Walker",
        "5dd5b0494fee5d8aac2480eab05b04fd"
    ],
    "Hiramato": [
        41972,
        "Neo: Dimension Walker",
        "0e8bc2ac53bb6e4b2b88d1270b540f5e"
    ],
    "Hotokekusai": [
        40045,
        "Neo: Dimension Walker",
        "8dd40c658c27def9001c3d91845e865c"
    ],
    "ICANFIXHIM": [
        40815,
        "Neo: Dimension Walker",
        "ab8dbb3d60a48cb36e742958e7540714"
    ],
    "ImoutoGa": [
        41860,
        "Neo: Dimension Walker",
        "823735908746bc64a159a2436f1f2aff"
    ],
    "JTeatime": [
        42000,
        "Neo: Dimension Walker",
        "6df3eda20944b7ca5b0f640638b11355"
    ],
    "Kryzal": [
        40527,
        "Neo: Dimension Walker",
        "a5bcdd0fe7d59236b685e2f90aedffc5"
    ],
    "LonelyFlow": [
        42705,
        "Neo: Dimension Walker",
        "8eb376a7c22711371b39a235f88534e6"
    ],
    "Lotus": [
        41743,
        "Neo: Dimension Walker",
        "09a0a21e7a57defdd53a4f2598c6ddcb"
    ],
    "Malthous": [
        43777,
        "Neo: Dimension Walker",
        "ca8a6dfae6b47f0e9f71cfc8cd5f806c"
    ],
    "Mapu": [
        46031,
        "Neo: Dimension Walker",
        "4e735129f99bb28d5e7828f4bb947c89"
    ],
    "MoeInvader": [
        43424,
        "Neo: Dimension Walker",
        "ee52b17c2fc3c7ffc8971b199217666d"
    ],
    "NyaRuby": [
        46946,
        "Neo: Dimension Walker",
        "1f0f54c0092e66e404d330236a16170c"
    ],
    "NyarlyPrPr": [
        44857,
        "Neo: Dimension Walker",
        "8f2208cdcb5a7b77babeecc91228e848"
    ],
    "Obalisk": [
        40243,
        "Neo: Dimension Walker",
        "2a1ef80f080180fc5aa3ada1da88dd83"
    ],
    "Periit": [
        46957,
        "Neo: Dimension Walker",
        "b7bfec43da066d240dfc17a2e1acf297"
    ],
    "PyrosMajin": [
        45772,
        "Neo: Dimension Walker",
        "bd71af7b229325aafc635999e8e11d3b"
    ],
    "RainWalker": [
        41012,
        "Neo: Dimension Walker",
        "eee57f012186ff7263047087c84b0e39"
    ],
    "Randulph": [
        40588,
        "Neo: Dimension Walker",
        "1bc83858d9838033f754f4d690976097"
    ],
    "Reis0lZero": [
        40628,
        "Neo: Dimension Walker",
        "83d229e8919d4dd5873dfc0194775981"
    ],
    "ReprobateZze": [
        44435,
        "Neo: Dimension Walker",
        "b4114df2d855fd460fe6175e036208aa"
    ],
    "RiftWalking": [
        44704,
        "Neo: Dimension Walker",
        "b8045e3be59076a145ded8360f6cecd4"
    ],
    "RuRuCorn": [
        41885,
        "Neo: Dimension Walker",
        "dfd16dcbbda0caf3782958e4036d80f8"
    ],
    "Rustikarl": [
        40448,
        "Neo: Dimension Walker",
        "c12206fd104a7ab7c3122f51cdcf2bf8"
    ],
    "Soell": [
        43248,
        "Neo: Dimension Walker",
        "617b0e687b58be074a5507519d89b571"
    ],
    "SoranLaby": [
        41939,
        "Neo: Dimension Walker",
        "9a32dce7aac8a995d4438daa695ec953"
    ],
    "SpaceSlime": [
        45771,
        "Neo: Dimension Walker",
        "b8e0fc80fdbdd1c0524d606a136c3c78"
    ],
    "TgYuri": [
        43029,
        "Neo: Dimension Walker",
        "6b343954fc418f417f0546049ba13ab5"
    ],
    "Vinasha": [
        43612,
        "Neo: Dimension Walker",
        "5ed85963fee79e119555d3c07a9c1e6f"
    ],
    "YaaJakab": [
        42182,
        "Neo: Dimension Walker",
        "1b32d44d81fee09354666bbe032750ba"
    ],
    "ZMAscendant": [
        44328,
        "Neo: Dimension Walker",
        "1bdeb0caab22e14423017446a87d0f12"
    ],
    "emobread": [
        43589,
        "Neo: Dimension Walker",
        "141000b94c456a654891cfd083603a66"
    ],
    "happyfanfan": [
        46319,
        "Neo: Dimension Walker",
        "f17d1705151d111daa9499d6ea730e09"
    ],
    "kapns": [
        47620,
        "Neo: Dimension Walker",
        "31ca9992d9fcff4567dbf8b38437e9f5"
    ],
    "nayokkke": [
        41747,
        "Neo: Dimension Walker",
        "1aa86527386c2ba4ed1aaa50ef6126ee"
    ],
    "savage5605": [
        40213,
        "Neo: Dimension Walker",
        "92a0b94178b57ef956d4adb4c5ff4f87"
    ],
    "whyhatemage": [
        42278,
        "Neo: Dimension Walker",
        "94c5016444d66881c35d146e0e3e81c7"
    ],
    "xehamios": [
        41307,
        "Neo: Dimension Walker",
        "39ea59fd590522328bb026924b1c9354"
    ],
    "zCataclysm": [
        45904,
        "Neo: Dimension Walker",
        "5f4d0cbb55b3e1abc5139ec00fb941a5"
    ]
}